pyquickstep/NetworkCli_pb2.py
pyquickstep/NetworkCli_pb2_grpc.py
pyquickstep/__init__.py
pyquickstep/connections.py
pyquickstep/cursor.py
pyquickstep/quickstepresult.py
pyquickstep/constants/COMMON.py
pyquickstep/constants/__init__.py
pyquickstep/error/__init__.py
pyquickstep/error/databaseerror.py
pyquickstep/error/error.py
pyquickstep/error/interfaceerror.py
pyquickstep/error/quicksteperror.py
pyquickstep/error/warning.py
PyQuickstep-1.0.6.dist-info/LICENSE
PyQuickstep-1.0.6.dist-info/METADATA
PyQuickstep-1.0.6.dist-info/WHEEL
PyQuickstep-1.0.6.dist-info/top_level.txt
PyQuickstep-1.0.6.dist-info/RECORD
